danbi_fastapi/Middleware.py
danbi_fastapi/RollByUrlpathAuth.py
danbi_fastapi/TortoiseORM.py
danbi_fastapi/UvicornServer.py
danbi_fastapi/__init__.py
danbi_fastapi-0.2.0.dist-info/METADATA
danbi_fastapi-0.2.0.dist-info/WHEEL
danbi_fastapi-0.2.0.dist-info/RECORD
